legos.codinglove-0.1.1-py3.3-nspkg.pth
legos/codinglove.py
legos.codinglove-0.1.1.dist-info/DESCRIPTION.rst
legos.codinglove-0.1.1.dist-info/METADATA
legos.codinglove-0.1.1.dist-info/RECORD
legos.codinglove-0.1.1.dist-info/WHEEL
legos.codinglove-0.1.1.dist-info/metadata.json
legos.codinglove-0.1.1.dist-info/namespace_packages.txt
legos.codinglove-0.1.1.dist-info/top_level.txt
